av_safety_parser/__init__.py
av_safety_parser/main.py
av_safety_parser/prompts.py
av_safety_parser-2025.12.21191556.dist-info/METADATA
av_safety_parser-2025.12.21191556.dist-info/WHEEL
av_safety_parser-2025.12.21191556.dist-info/top_level.txt
av_safety_parser-2025.12.21191556.dist-info/RECORD
