Metadata-Version: 2.4
Name: av-safety-parser
Version: 2025.12.21191556
Summary: av-safety-parser extracts aviation incident details from unstructured text, outputting standardized data on incident type, aircraft, and risks.
Author-email: av-safety-parser <hi@eugene.plus>
License: MIT
Project-URL: Homepage, https://github.com/chigwell/av-safety-parser
Requires-Python: >=3.9
Requires-Dist: langchain-llm7>=0.0.0
Requires-Dist: llmatch-messages>=0.0.0
Requires-Dist: langchain-core>=0.3.0
